webinfo_retriever/__init__.py
webinfo_retriever/cli.py
webinfo_retriever/api/__init__.py
webinfo_retriever/api/client.py
webinfo_retriever/api/search_client.py
webinfo_retriever/core/__init__.py
webinfo_retriever/core/advanced_search_engine.py
webinfo_retriever/core/ai_processor.py
webinfo_retriever/core/analytics_engine.py
webinfo_retriever/core/answer_formatter.py
webinfo_retriever/core/content_extractor.py
webinfo_retriever/core/intelligent_search.py
webinfo_retriever/core/markdown_formatter.py
webinfo_retriever/core/query_processor.py
webinfo_retriever/core/response_generator.py
webinfo_retriever/core/scraper.py
webinfo_retriever/core/search_processor.py
webinfo_retriever/core/smart_cache.py
webinfo_retriever/dashboard/__init__.py
webinfo_retriever/dashboard/app.py
webinfo_retriever/utils/__init__.py
webinfo_retriever/utils/config.py
webinfo_retriever/utils/exceptions.py
webinfo_retriever/utils/validators.py
webinfo_retriever-2.1.0.dist-info/licenses/LICENSE
webinfo_retriever-2.1.0.dist-info/METADATA
webinfo_retriever-2.1.0.dist-info/WHEEL
webinfo_retriever-2.1.0.dist-info/entry_points.txt
webinfo_retriever-2.1.0.dist-info/top_level.txt
webinfo_retriever-2.1.0.dist-info/RECORD
