Metadata-Version: 2.4
Name: webinfo-retriever
Version: 2.1.0
Summary: Ultra-fast comprehensive web search and AI-powered analysis with parallel processing
Home-page: https://github.com/JustM3Sunny/AI_WEB_INFO_RETRIVAL
Author: JustM3Sunny
Author-email: JustM3Sunny <justaskcoding76@gmail.com>
License: MIT
Project-URL: Homepage, https://github.com/webinfo-retriever/webinfo-retriever
Project-URL: Documentation, https://webinfo-retriever.readthedocs.io/
Project-URL: Repository, https://github.com/webinfo-retriever/webinfo-retriever
Project-URL: Bug Tracker, https://github.com/webinfo-retriever/webinfo-retriever/issues
Keywords: web scraping,ai summarization,information retrieval,gemini ai,content extraction
Classifier: Development Status :: 5 - Production/Stable
Classifier: Intended Audience :: Developers
Classifier: License :: OSI Approved :: MIT License
Classifier: Operating System :: OS Independent
Classifier: Programming Language :: Python :: 3
Classifier: Programming Language :: Python :: 3.8
Classifier: Programming Language :: Python :: 3.9
Classifier: Programming Language :: Python :: 3.10
Classifier: Programming Language :: Python :: 3.11
Classifier: Programming Language :: Python :: 3.12
Classifier: Topic :: Internet :: WWW/HTTP :: Indexing/Search
Classifier: Topic :: Scientific/Engineering :: Artificial Intelligence
Classifier: Topic :: Software Development :: Libraries :: Python Modules
Requires-Python: >=3.8
License-File: LICENSE
Requires-Dist: requests>=2.31.0
Requires-Dist: beautifulsoup4>=4.12.0
Requires-Dist: lxml>=4.9.0
Requires-Dist: selenium>=4.15.0
Requires-Dist: google-generativeai>=0.3.0
Requires-Dist: aiohttp>=3.9.0
Requires-Dist: asyncio-throttle>=1.0.2
Requires-Dist: readability-lxml>=0.8.1
Requires-Dist: python-dotenv>=1.0.0
Requires-Dist: validators>=0.22.0
Requires-Dist: fake-useragent>=1.4.0
Requires-Dist: urllib3>=2.0.0
Requires-Dist: chardet>=5.2.0
Requires-Dist: html5lib>=1.1
Requires-Dist: newspaper3k>=0.2.8
Requires-Dist: trafilatura>=1.6.0
Requires-Dist: markdownify>=0.11.6
Requires-Dist: python-dateutil>=2.8.0
Requires-Dist: cachetools>=5.3.0
Requires-Dist: tenacity>=8.2.0
Provides-Extra: dev
Requires-Dist: pytest>=7.0.0; extra == "dev"
Requires-Dist: pytest-asyncio>=0.21.0; extra == "dev"
Requires-Dist: black>=23.0.0; extra == "dev"
Requires-Dist: flake8>=6.0.0; extra == "dev"
Requires-Dist: mypy>=1.0.0; extra == "dev"
Dynamic: author
Dynamic: home-page
Dynamic: license-file
Dynamic: requires-python
